Metadata-Version: 2.1
Name: simplepycuda
Version: 0.0.1
Summary: A simple wrapper for CUDA functions in Python.
Home-page: https://github.com/igormcoelho/simple-pycuda
Author: Igor Machado and Rodolfo Araujo
Author-email: igor.machado@ime.uerj.br
License: MIT
Platform: UNKNOWN
Classifier: Programming Language :: Python :: 2
Classifier: License :: OSI Approved :: MIT License
